rtl/pump_fsm.v
module pump_fsm(

    input wire clk,
    input wire reset,
    input wire dry,

    output reg pump_on

);

//-----------------------------
// State Encoding
//-----------------------------

parameter IDLE       = 2'b00;
parameter START_PUMP = 2'b01;
parameter WATERING   = 2'b10;
parameter STOP_PUMP  = 2'b11;

reg [1:0] current_state;
reg [1:0] next_state;

//-----------------------------
// State Register
//-----------------------------

always @(posedge clk or posedge reset)
begin
    if(reset)
        current_state <= IDLE;
    else
        current_state <= next_state;
end

//-----------------------------
// Next State Logic
//-----------------------------

always @(*)
begin

    case(current_state)

        IDLE:
            if(dry)
                next_state = START_PUMP;
            else
                next_state = IDLE;

        START_PUMP:
            next_state = WATERING;

        WATERING:
            if(dry)
                next_state = WATERING;
            else
                next_state = STOP_PUMP;

        STOP_PUMP:
            next_state = IDLE;

        default:
            next_state = IDLE;

    endcase

end

//-----------------------------
// Output Logic
//-----------------------------

always @(*)
begin

    case(current_state)

        IDLE:
            pump_on = 0;

        START_PUMP:
            pump_on = 1;

        WATERING:
            pump_on = 1;

        STOP_PUMP:
            pump_on = 0;

        default:
            pump_on = 0;

    endcase

end

endmodule

tb/pump_fsm_tb.v
`timescale 1ns/1ps

module pump_fsm_tb;

    // Inputs
    reg clk;
    reg reset;
    reg dry;

    // Output
    wire pump_on;

    integer pass_count = 0;
    integer fail_count = 0;

    // Instantiate the Design Under Test (DUT)
    pump_fsm uut (
        .clk(clk),
        .reset(reset),
        .dry(dry),
        .pump_on(pump_on)
    );

    // Clock Generation (10 ns period)
    always #5 clk = ~clk;

    // Task to check pump output
    task check_output;
        input expected;
        begin
            #1;
            if (pump_on == expected) begin
                $display("PASS : Time=%0t Dry=%0b Pump=%0b",
                         $time, dry, pump_on);
                pass_count = pass_count + 1;
            end
            else begin
                $display("FAIL : Time=%0t Dry=%0b Expected=%0b Got=%0b",
                         $time, dry, expected, pump_on);
                fail_count = fail_count + 1;
            end
        end
    endtask

    initial begin

        // Waveform generation
        $dumpfile("waveforms/pump_fsm.vcd");
        $dumpvars(0, pump_fsm_tb);

        $display("=======================================");
        $display("      Pump FSM Verification");
        $display("=======================================");

        clk = 0;
        reset = 1;
        dry = 0;

        // Reset FSM
        #12;
        reset = 0;

        //-------------------------------------------------
        // Test Case 1 : Soil is Wet
        //-------------------------------------------------
        dry = 0;
        #10;
        check_output(0);

        //-------------------------------------------------
        // Test Case 2 : Soil becomes Dry
        //-------------------------------------------------
        dry = 1;

        #10;      // START_PUMP
        check_output(1);

        #10;      // WATERING
        check_output(1);

        //-------------------------------------------------
        // Test Case 3 : Soil becomes Wet again
        //-------------------------------------------------
        dry = 0;

        #10;      // STOP_PUMP
        check_output(0);

        #10;      // IDLE
        check_output(0);

        //-------------------------------------------------

        $display("---------------------------------------");
        $display("PASS = %0d", pass_count);
        $display("FAIL = %0d", fail_count);
        $display("---------------------------------------");

        if (fail_count == 0)
            $display("ALL TEST CASES PASSED");
        else
            $display("SOME TEST CASES FAILED");

        $finish;

    end

endmodule

pump_fsm.vcd
$date
	Wed Jul  1 15:09:53 2026
$end
$version
	Icarus Verilog
$end
$timescale
	1ps
$end
$scope module pump_fsm_tb $end
$var wire 1 ! pump_on $end
$var reg 1 " clk $end
$var reg 1 # dry $end
$var reg 1 $ reset $end
$var integer 32 % fail_count [31:0] $end
$var integer 32 & pass_count [31:0] $end
$scope module uut $end
$var wire 1 " clk $end
$var wire 1 # dry $end
$var wire 1 $ reset $end
$var parameter 2 ' IDLE $end
$var parameter 2 ( START_PUMP $end
$var parameter 2 ) STOP_PUMP $end
$var parameter 2 * WATERING $end
$var reg 2 + current_state [1:0] $end
$var reg 2 , next_state [1:0] $end
$var reg 1 ! pump_on $end
$upscope $end
$scope task check_output $end
$var reg 1 - expected $end
$upscope $end
$upscope $end
$enddefinitions $end
$comment Show the parameter values. $end
$dumpall
b10 *
b11 )
b1 (
b0 '
$end
#0
$dumpvars
x-
b0 ,
b0 +
b0 &
b0 %
1$
0#
0"
0!
$end
#5000
1"
#10000
0"
#12000
0$
#15000
1"
#20000
0"
#22000
0-
#23000
b1 ,
1#
b1 &
#25000
1!
b10 ,
b1 +
1"
#30000
0"
#33000
1-
#34000
b10 &
#35000
b10 +
1"
#40000
0"
#45000
b11 ,
0#
b11 &
1"
#50000
0"
#55000
0!
b0 ,
b11 +
1"
0-
#56000
b100 &
#60000
0"
#65000
b0 +
1"
#67000
b101 &
